{
  "schema_version": "v75.0",
  "generated_at": "2026-05-01T18:45:00Z",
  "admin_mode": "enabled_scaffold",
  "direct_editing": "disabled_in_static_bundle",
  "patch_export": "enabled_via_scripts",
  "protected_counts": {
    "items": 476,
    "sources": 382,
    "families": 10,
    "needs_review_families": 5
  },
  "review_queue_counts": {
    "candidates": 38,
    "duplicate_clusters": 8,
    "incidents_pending": 4
  },
  "recommended_next_admin_tasks": [
    "Review new v77 discovery candidates",
    "Capture archive URLs for high-impact coverage",
    "Confirm relationships for needs_review families",
    "Export reviewed patches only after QA passes"
  ]
}
